[{"name": "archos oxygen 68 xl"}, {"name": "archos oxygen 63"}, {"name": "archos oxygen 57"}, {"name": "archos diamond"}, {"name": "archos access 50 s"}, {"name": "archos access 57"}, {"name": "archos core 57s"}, {"name": "archos core 60s"}, {"name": "archos core 55s"}, {"name": "archos diamond omega"}, {"name": "archos 45 access 4g"}, {"name": "archos core 50"}, {"name": "archos diamond alpha"}, {"name": "archos diamond gamma"}, {"name": "archos sense 50x"}, {"name": "archos 55 graphite"}, {"name": "archos 55b cobalt"}, {"name": "archos 50b cobalt"}, {"name": "archos 55 diamond selfie"}, {"name": "archos 50 titanium"}, {"name": "archos 55 helium ultra"}, {"name": "archos 50f helium"}, {"name": "archos 50 saphir"}, {"name": "archos 50e neon"}, {"name": "archos 50 power"}, {"name": "archos 50 helium+"}, {"name": "archos 60 platinum"}, {"name": "archos diamond plus"}, {"name": "archos 50f neon"}, {"name": "archos 40 neon"}, {"name": "archos 55 cobalt+"}, {"name": "archos 50 cobalt"}, {"name": "archos 50d neon"}, {"name": "archos 45c helium"}, {"name": "archos 50 platinum 4g"}, {"name": "archos diamond 2 plus"}, {"name": "archos 55b platinum"}, {"name": "archos 40 power"}, {"name": "archos diamond s"}, {"name": "archos 55 platinum"}, {"name": "archos 50e helium"}, {"name": "archos 53 platinum"}, {"name": "archos 50c platinum"}, {"name": "archos 50 cesium"}, {"name": "archos 55 helium+"}, {"name": "archos 52 platinum"}, {"name": "archos 50d helium 4g"}, {"name": "archos 40d titanium"}, {"name": "archos 55 helium"}, {"name": "archos 50c neon"}, {"name": "archos 50d oxygen"}, {"name": "archos 50d oxygen plus"}, {"name": "archos 50c oxygen"}, {"name": "archos 50 diamond"}, {"name": "archos 50c helium"}, {"name": "archos 45b helium 4g"}, {"name": "archos 50b helium 4g"}, {"name": "archos 59 titanium"}, {"name": "archos 40c titanium"}, {"name": "archos 64 xenon"}, {"name": "archos 50b oxygen"}, {"name": "archos 50b platinum"}]